{"type":"PR","pr":{"number":6,"head":"bfb9dc9dfbd714129ecf8d5ad6f78512d2456ac9"},"user":"joe","status":"draft","branch":"cms/globals/meta","collection":"globals","commitMessage":"Update Global Settings “meta”","title":"Sylvarna Kitchen Design","description":"Lorem ipsum dolor sit amet, consectetur adipiscing elit, sed do eiusmod tempor incididunt ut labore et dolore magna aliqua.","objects":{"entry":{"path":"src/_data/meta.json","sha":"631cee209db3e574f5abceda9c869d9f26459796"},"files":[]},"timeStamp":"2019-12-31T18:04:05.933Z","version":"1"}